{
  "id": "vozdyizhenie-kresta",
  "title": "Воздвижение Креста Господня",
  "icon": "data/vozdyizhenie-kresta/images/Воздвижение_Креста.png",
  "description": "Тест о обретении и воздвижении Честного Креста Господня",
  "questions": [
    {
      "id": 1,
      "text": "Когда празднуется Воздвижение Креста Господня?",
      "options": [
        "25 декабря",
        "27 сентября",
        "7 января",
        "14 февраля"
      ],
      "correct": 1
    },
    {
      "id": 2,
      "text": "Кто нашёл Крест Христов в 326 году?",
      "options": [
        "Император Константин",
        "Царица Елена",
        "Апостол Пётр",
        "Патриарх Макарий"
      ],
      "correct": 1
    },
    {
      "id": 3,
      "text": "Какое чудесное знамение увидел император Константин перед битвой?",
      "options": [
        "Светящийся крест с надписью «Сим победишь»",
        "Ангела с мечом",
        "Огненную колесницу",
        "Радугу на небе"
      ],
      "correct": 0
    },
    {
      "id": 4,
      "text": "Сколько крестов нашли в земле рядом с Голгофой?",
      "options": [
        "Один",
        "Два",
        "Три",
        "Четыре"
      ],
      "correct": 2
    },
    {
      "id": 5,
      "text": "Как узнали, какой из трёх крестов — Крест Христов?",
      "options": [
        "По особой форме дерева",
        "По найденной рядом табличке",
        "По чуду исцеления больной",
        "Путём жеребьёвки"
      ],
      "correct": 2
    },
    {
      "id": 6,
      "text": "Что означает слово «воздвижение»?",
      "options": [
        "Украшение креста цветами",
        "Поднятие вверх, чтобы все видели",
        "Процессия вокруг храма",
        "Пост в течение трёх дней"
      ],
      "correct": 1
    },
    {
      "id": 7,
      "text": "Кто вернул честной Крест из Персии в Иерусалим в 628 году?",
      "options": [
        "Император Константин",
        "Император Ираклий",
        "Царь Хозрой",
        "Патриарх Захария"
      ],
      "correct": 1
    },
    {
      "id": 8,
      "text": "Почему император Ираклий сначала не смог войти с Крестом в храм?",
      "options": [
        "Двери храма были закрыты",
        "Он устал после дороги",
        "Он был в царских одеждах и не проявил смирения",
        "Ему запретил вход стражник"
      ],
      "correct": 2
    },
    {
      "id": 9,
      "text": "Что совершает священник в храме в этот праздник?",
      "options": [
        "Воздвигает (поднимает) крест для поклонения",
        "Омывает крест водой",
        "Несёт крест вокруг города",
        "Прячет крест до Пасхи"
      ],
      "correct": 0
    },
    {
      "id": 10,
      "text": "Что означает выражение «нести свой крест»?",
      "options": [
        "Носить большой нательный крест",
        "Часто путешествовать по святым местам",
        "Строить храмы и помогать монастырям",
        "Терпеливо переносить трудности с верой"
      ],
      "correct": 3
    }
  ]
}

